{
  "config": {
    "nav": {
      "mtn": {
        "description": "New Transformer Manufacturing",
        "submenu": {
          "productos": "Products",
          "transformadores": "Transformers",
          "tipoPoste": "Pole Type",
          "padMounted": "Pad Mounted",
          "subestacion": "Substation",
          "secosResina": "Resin-Cast Dry Type",
          "normativa": "Standards",
          "certificaciones": "Certifications",
          "recursos": "Resources",
          "cotizaciones": "Quotes"
        }
      },
      "etrys": {
        "description": "Transformer Repair and Service",
        "submenu": {
          "reparacion": "Repair",
          "remanufacturados": "Remanufactured",
          "alquiler": "Rental",
          "recursos": "Resources",
          "cotizaciones": "Quotes"
        }
      },
      "eic": {
        "description": "Eminsa International Corporation",
        "submenu": {
          "productos": "Products",
          "transformadores": "Transformers",
          "cables": "Cables",
          "distribucionMT": "MV Distribution",
          "breakersProteccion": "Breakers & Protection",
          "accesorios": "Accessories",
          "marcas": "Brands",
          "recursos": "Resources",
          "cotizaciones": "Quotes"
        }
      },
      "servicios": {
        "name": "Services",
        "description": "Specialized Technical Services",
        "submenu": {
          "preventivo": "Preventive - Predictive",
          "correctivo": "Field Corrective",
          "mantenimiento": "Comprehensive Maintenance",
          "emergencias": "Emergencies",
          "ingenieria": "Engineering & Projects",
          "laboratorio": "Laboratory Testing",
          "alquiler": "Equipment Rental",
          "cotizaciones": "Quotes"
        }
      },
      "eminsa": {
        "description": "Learn About Grupo EMINSA",
        "submenu": {
          "sobreNosotros": "About Us",
          "proyectos": "Projects",
          "noticias": "News",
          "contacto": "Contact"
        }
      }
    },
    "divisions": {
      "mtn": {
        "fullName": "New Transformer Manufacturing",
        "tagline": "New Transformer Manufacturing",
        "description": "Electrical transformation solutions with high-performance technology, guaranteed efficiency, and local manufacturing under ANSI and DOE 2016 standards.",
        "features": {
          "0": "Pole Type Transformers",
          "1": "Pad Mounted",
          "2": "Substation",
          "3": "ISO 9001 Certification"
        }
      },
      "etrys": {
        "fullName": "Transformer Repair and Service",
        "tagline": "Transformer Repair and Service",
        "description": "At RST, we combine the experience of a highly qualified technical team with cutting-edge technology to give your transformers a new life.",
        "features": {
          "0": "Specialized Repair",
          "1": "Remanufactured Transformers",
          "2": "Equipment Rental",
          "3": "18-Month Warranty"
        }
      },
      "eic": {
        "fullName": "Eminsa International Corporation",
        "tagline": "Eminsa International Corporation",
        "description": "We connect Eminsa with the world, expanding our energy solutions through a solid global network of strategic allies, ensuring international presence, specialized service, and close support on every project.",
        "features": {
          "0": "INATRA",
          "1": "Schneider Electric",
          "2": "Hammond",
          "3": "Top Cable"
        }
      },
      "servicios": {
        "name": "SERVICES",
        "fullName": "EMINSA Services",
        "tagline": "Comprehensive Field Solutions",
        "description": "SERVICES is Grupo EMINSA's business unit focused on providing specialized on-site technical support, offering maintenance, repair, and comprehensive support to ensure the efficiency, safety, and operational continuity of our clients' electrical transformers.",
        "features": {
          "0": "Preventive Maintenance",
          "1": "24/7 Emergencies",
          "2": "Laboratory Testing",
          "3": "Project Engineering"
        }
      }
    },
    "stats": {
      "0": { "label": "Years of Experience" },
      "1": { "label": "Transformers Installed" },
      "2": { "label": "Satisfied Clients" },
      "3": { "label": "Technical Support" }
    },
    "contactInfo": {
      "address": "Santo Domingo, Dominican Republic"
    },
    "services": {
      "preventivo": {
        "name": "Preventive - Predictive Maintenance",
        "shortName": "Preventive",
        "description": "Scheduled inspections, diagnostic testing, and condition monitoring to anticipate failures and extend the useful life of your equipment.",
        "benefits": {
          "0": "Prevention of unexpected failures",
          "1": "Greater transformer availability",
          "2": "Reduced repair costs",
          "3": "Extended useful life"
        }
      },
      "correctivo": {
        "name": "Field Corrective Maintenance",
        "shortName": "Corrective",
        "description": "On-site corrective maintenance solutions, ensuring quick and efficient response to failures.",
        "benefits": {
          "0": "Cosmetic rehabilitation",
          "1": "Oil restoration",
          "2": "Leak correction",
          "3": "Component replacement"
        }
      },
      "integral": {
        "name": "Comprehensive Maintenance",
        "shortName": "Comprehensive",
        "description": "Complete service combining inspection, execution, and final verification for maximum reliability.",
        "benefits": {
          "0": "Prior technical inspection",
          "1": "Findings-based maintenance",
          "2": "Post-maintenance inspection",
          "3": "Future failure prevention"
        }
      },
      "emergencias": {
        "name": "Emergency Response",
        "shortName": "Emergencies",
        "description": "Specialized rapid response service for critical situations, available 24/7.",
        "benefits": {
          "0": "Immediate response",
          "1": "On-site inspection",
          "2": "Corrective actions",
          "3": "Technical reports"
        }
      },
      "ingenieria": {
        "name": "Engineering and Project Management",
        "shortName": "Engineering",
        "description": "Comprehensive solutions from design to execution of complex electrical projects.",
        "benefits": {
          "0": "Facility design",
          "1": "Electrical assemblies",
          "2": "Large-scale projects",
          "3": "Specialized supervision"
        }
      },
      "laboratorio": {
        "name": "Laboratory Testing",
        "shortName": "Laboratory",
        "description": "Specialized dielectric oil analysis in partnership with SD Myers, a world leader in diagnostics.",
        "benefits": {
          "0": "Dissolved gas analysis",
          "1": "Dielectric strength",
          "2": "Moisture detection",
          "3": "Results interpretation"
        }
      },
      "alquiler": {
        "name": "Transformer Rental",
        "shortName": "Rental",
        "description": "Equipment available to cover temporary needs or respond to emergencies.",
        "benefits": {
          "0": "Immediate availability",
          "1": "Flexible options",
          "2": "Installation included",
          "3": "Cost-effective alternative"
        }
      }
    },
    "certifications": {
      "iso9001": { "description": "Quality Management System" },
      "iqnet": { "description": "International Certification Network" },
      "cidet": { "description": "Center for Research and Technological Development" },
      "ul": { "description": "Underwriters Laboratories" }
    },
    "standards": {
      "ansi": { "description": "American standards for transformers" },
      "doe2016": { "description": "DOE energy efficiency standards" },
      "ieeeC57": { "description": "IEEE standards for power transformers" },
      "iso9001": { "description": "Quality management system" }
    },
    "mtnProducts": {
      "tipoPoste": {
        "name": "Pole Type Transformers",
        "description": "Distribution transformers for pole-mounted installation",
        "types": {
          "monofasicos": "Single-Phase",
          "trifasicos": "Three-Phase",
          "autoprotegidos": "Self-Protected"
        }
      },
      "padMounted": {
        "name": "Pad Mounted Transformers",
        "description": "Pedestal-type transformers for ground-level installation",
        "types": {
          "monofasicos": "Single-Phase",
          "trifasicos": "Three-Phase"
        }
      },
      "subestacion": {
        "name": "Substation Transformers",
        "description": "Power transformers for electrical substations"
      },
      "secosResina": {
        "name": "Resin-Cast Dry Type Transformers",
        "description": "Resin-encapsulated transformers for special environments"
      }
    }
  },
  "servicios": {
    "info": {
      "tagline": "Comprehensive Field Solutions",
      "slogan": "More than 50 years of experience and service",
      "description": "SERVICES is Grupo EMINSA's business unit focused on providing specialized on-site technical support, offering maintenance, repair, and comprehensive support to ensure the efficiency, safety, and operational continuity of our clients' electrical transformers.",
      "stats": {
        "0": { "label": "Years of Experience" },
        "1": { "label": "Clients Served" },
        "2": { "label": "Technical Support" },
        "3": { "label": "Satisfaction" }
      },
      "proceso": {
        "1": {
          "titulo": "Technical Inspection",
          "descripcion": "Assessment of current conditions, detection of potential risks, and preparation of a comprehensive equipment diagnosis."
        },
        "2": {
          "titulo": "Specialized Execution",
          "descripcion": "Findings-based maintenance: work execution according to the results of the initial diagnosis."
        },
        "3": {
          "titulo": "Final Verification",
          "descripcion": "Validation of the work performed, confirmation of transformer operability, and delivery of a technical report."
        }
      }
    },
    "detalle": {
      "preventivo": {
        "nombre": "Preventive - Predictive Maintenance",
        "nombreCorto": "Preventive",
        "descripcion": "Scheduled inspections, diagnostic testing, and condition monitoring to anticipate failures and extend the useful life of your equipment.",
        "descripcionLarga": "At EMINSA Services, we understand that the reliability of your transformers is key to the continuity of your operations. Our Preventive and Predictive Maintenance program is designed to anticipate failures, minimize risks, and extend the useful life of your equipment. Through scheduled inspections, diagnostic testing, and condition monitoring, we ensure that each transformer operates at optimal parameters, reducing unplanned downtime and optimizing operating costs.",
        "beneficios": {
          "0": "Prevention of unexpected failures",
          "1": "Greater transformer availability and efficiency",
          "2": "Reduction of major repair costs",
          "3": "Extension of equipment useful life",
          "4": "Safety and continuity in power distribution"
        },
        "etapas": {
          "0": {
            "titulo": "Visual and Thermographic Inspection",
            "descripcion": "Assessment of external condition, connections, bushings, and components using infrared thermography."
          },
          "1": {
            "titulo": "Diagnostic Testing",
            "descripcion": "Dielectric oil analysis, insulation resistance measurement, power factor, and turns ratio testing."
          },
          "2": {
            "titulo": "Condition Monitoring",
            "descripcion": "Continuous tracking of critical parameters to detect degradation trends."
          },
          "3": {
            "titulo": "Report and Recommendations",
            "descripcion": "Delivery of a detailed technical report with findings, diagnosis, and recommended action plan."
          }
        }
      },
      "correctivo": {
        "nombre": "Field Corrective Maintenance",
        "nombreCorto": "Corrective",
        "descripcion": "On-site corrective maintenance solutions, ensuring quick and efficient response to failures.",
        "descripcionLarga": "At EMINSA Services, we offer on-site corrective maintenance solutions, ensuring quick and efficient response to failures or conditions that compromise the operation of your transformers. Our specialized technicians are trained to intervene directly in the field, reducing downtime and avoiding unnecessary equipment transport.",
        "beneficios": {
          "0": "Quick and efficient on-site response",
          "1": "Reduced downtime",
          "2": "Avoids unnecessary equipment transport",
          "3": "Restoration of operational reliability",
          "4": "Operational continuity"
        },
        "alcance": {
          "0": "Cosmetic rehabilitation: paint application and label replacement",
          "1": "Oil level restoration and adjustment",
          "2": "Dielectric oil change",
          "3": "Leak detection and correction",
          "4": "Replacement of critical components (bushings, inserts, breathers, valves, connectors)"
        }
      },
      "integral": {
        "nombre": "Comprehensive Field Maintenance",
        "nombreCorto": "Comprehensive",
        "descripcion": "Complete service combining inspection, execution, and final verification for maximum reliability.",
        "descripcionLarga": "Our Comprehensive Field Maintenance service guarantees complete transformer care, combining inspection, execution, and final verification to ensure maximum equipment reliability. This service is designed to cover all phases necessary in transformer care: from initial assessment to post-maintenance verification.",
        "beneficios": {
          "0": "Correction of existing conditions",
          "1": "Prevention of future failures",
          "2": "Extension of equipment useful life",
          "3": "Optimization of electrical system operation",
          "4": "Complete technical report"
        },
        "etapas": {
          "0": {
            "titulo": "Prior Technical Inspection",
            "descripcion": "Assessment of current conditions and detection of potential risks."
          },
          "1": {
            "titulo": "Findings-Based Maintenance",
            "descripcion": "Execution of work according to the results of the initial diagnosis."
          },
          "2": {
            "titulo": "Post-Maintenance Technical Inspection",
            "descripcion": "Validation of work performed and confirmation of transformer operability."
          }
        }
      },
      "revisiones": {
        "nombre": "Technical Reviews and Diagnostics",
        "nombreCorto": "Reviews",
        "descripcion": "Specialized technical evaluations to determine the actual condition and remaining useful life of your transformers.",
        "descripcionLarga": "Our Technical Reviews and Diagnostics service provides a thorough assessment of your transformers' condition. We use state-of-the-art equipment and advanced diagnostic techniques to precisely determine operating conditions, identify potential problems, and recommend corrective or preventive actions.",
        "beneficios": {
          "0": "Accurate diagnosis of equipment condition",
          "1": "Early identification of problems",
          "2": "Data for maintenance planning",
          "3": "Remaining useful life assessment",
          "4": "Detailed technical reports"
        },
        "etapas": {
          "0": {
            "titulo": "Dielectric Oil Analysis",
            "descripcion": "Physicochemical tests, dissolved gas chromatography, and furan analysis."
          },
          "1": {
            "titulo": "Electrical Testing",
            "descripcion": "Insulation resistance measurement, power factor, turns ratio, and winding resistance."
          },
          "2": {
            "titulo": "Thermographic Inspection",
            "descripcion": "Detection of hot spots, loose connections, and overheating components."
          },
          "3": {
            "titulo": "Structural Assessment",
            "descripcion": "Inspection of tank, radiators, bushings, valves, and external accessories."
          }
        }
      },
      "asesoria": {
        "nombre": "Technical Advisory",
        "nombreCorto": "Advisory",
        "descripcion": "Specialized consulting to optimize the management of your electrical assets and maximize return on investment.",
        "descripcionLarga": "Our team of engineers and specialists offers comprehensive technical advisory to help you make the best decisions about your transformers and electrical systems. From equipment selection to maintenance planning, we accompany you at every stage to maximize the efficiency and reliability of your infrastructure.",
        "beneficios": {
          "0": "Optimization of asset management",
          "1": "Strategic maintenance planning",
          "2": "Proper equipment selection",
          "3": "Reduction of operating costs",
          "4": "Guaranteed regulatory compliance"
        }
      },
      "especiales": {
        "nombre": "Special Services",
        "nombreCorto": "Special",
        "descripcion": "Customized solutions for unique requirements that go beyond conventional maintenance.",
        "descripcionLarga": "EMINSA Services offers tailored solutions to meet our clients' special requirements. Whether it is equipment relocation, component modernization, or a particular intervention, we have the experience and resources to execute any special project related to electrical transformers.",
        "beneficios": {
          "0": "Customized solutions",
          "1": "Specialized technical team",
          "2": "Execution flexibility",
          "3": "Comprehensive project management",
          "4": "Quality guarantee"
        }
      },
      "emergencias": {
        "nombre": "Emergency Response",
        "nombreCorto": "Emergencies",
        "descripcion": "Specialized rapid response service for critical situations, available 24/7.",
        "descripcionLarga": "We understand that emergencies have no schedule. Our rapid response team is available 24 hours a day, 7 days a week, to handle any critical situation that puts your transformers' operation at risk. We guarantee minimal response times and effective actions to restore normal operation as quickly as possible.",
        "beneficios": {
          "0": "Immediate 24/7 response",
          "1": "Dedicated emergency team",
          "2": "Minimal response times",
          "3": "On-site corrective actions",
          "4": "Post-emergency technical reports"
        }
      },
      "ingenieria": {
        "nombre": "Engineering and Project Management",
        "nombreCorto": "Engineering",
        "descripcion": "Comprehensive solutions from design to execution of complex electrical projects.",
        "descripcionLarga": "Our engineering department offers complete design, planning, and management services for electrical projects. From substations to distribution systems, we cover all project stages ensuring quality, regulatory compliance, and execution efficiency.",
        "beneficios": {
          "0": "Electrical facility design",
          "1": "Assembly and commissioning",
          "2": "Large-scale projects",
          "3": "Specialized supervision",
          "4": "Regulatory compliance"
        },
        "etapas": {
          "0": {
            "titulo": "Study and Design",
            "descripcion": "Requirements analysis, solution design, and preparation of plans and technical specifications."
          },
          "1": {
            "titulo": "Planning and Logistics",
            "descripcion": "Activity scheduling, resource management, and client coordination."
          },
          "2": {
            "titulo": "Execution and Assembly",
            "descripcion": "Equipment installation, wiring, connections, and commissioning tests."
          },
          "3": {
            "titulo": "Commissioning",
            "descripcion": "Energization, functional testing, and formal project delivery with technical documentation."
          }
        }
      },
      "laboratorio": {
        "nombre": "Laboratory Testing",
        "nombreCorto": "Laboratory",
        "descripcion": "Specialized dielectric oil analysis in partnership with SD Myers, a world leader in diagnostics.",
        "descripcionLarga": "In partnership with SD Myers, the world leader in transformer diagnostics, we offer a complete dielectric oil analysis and laboratory testing service. Our results enable informed decisions about the maintenance and operation of your equipment, anticipating problems before they become costly failures.",
        "beneficios": {
          "0": "Dissolved Gas Analysis (DGA)",
          "1": "Dielectric strength and power factor",
          "2": "Moisture and particle detection",
          "3": "Furan analysis (paper useful life)",
          "4": "Expert interpretation of results"
        }
      },
      "alquiler": {
        "nombre": "Transformer Rental",
        "nombreCorto": "Rental",
        "descripcion": "Equipment available to cover temporary needs or respond to emergencies.",
        "descripcionLarga": "We have a large inventory of transformers available for temporary rental. Whether for construction projects, industrial expansions, scheduled maintenance, or emergencies, we offer flexible solutions with fast delivery, installation included, and 24/7 technical support.",
        "beneficios": {
          "0": "Immediate availability",
          "1": "Flexible contract options",
          "2": "Installation included",
          "3": "24/7 technical support",
          "4": "Cost-effective alternative"
        }
      }
    },
    "equipamiento": {
      "lab": {
        "name": "Electrical Testing Laboratory",
        "description": "Laboratory equipped in accordance with ANSI C.57 standards to ensure the quality of every service"
      },
      "horno": {
        "name": "Drying Oven",
        "description": "Industrial oven for drying transformer cores and coils"
      },
      "deshidratadores": {
        "name": "Oil Dehydrators",
        "description": "Vacuum oil dehydration system for purification"
      },
      "grua": {
        "name": "Overhead Crane",
        "description": "Overhead crane for safe handling of heavy transformers in the workshop"
      },
      "taller": {
        "name": "Manufacturing Workshop",
        "description": "Complete workshop with professional paint booth for high-quality finishes"
      },
      "montacargas": {
        "name": "Industrial Forklift",
        "description": "High-capacity forklift for handling heavy equipment"
      },
      "almacen": {
        "name": "Component Warehouse",
        "description": "Complete inventory of components and spare parts for immediate availability"
      },
      "tanque": {
        "name": "Storage Tank",
        "description": "Large-capacity dielectric fluid storage tank"
      }
    },
    "proyectos": {
      "p1": {
        "titulo": "Preventive Maintenance - Industrial Free Trade Zone",
        "cliente": "Zona Franca Las Americas",
        "ubicacion": "Santo Domingo Este, Dominican Republic",
        "tipoServicio": "Preventive Maintenance",
        "tipoProducto": "Distribution Transformers",
        "descripcion": "Comprehensive preventive maintenance program for 50 distribution transformers in an industrial free trade zone.",
        "detalles": "A preventive-predictive maintenance program was implemented that included quarterly thermographic inspections, semi-annual dielectric oil analysis, routine electrical testing, and continuous monitoring of operating conditions. The program reduced unplanned failures by 85% during the first year of implementation.",
        "resultados": {
          "0": "85% reduction in unplanned failures",
          "1": "30% reduction in maintenance costs",
          "2": "Zero critical service interruptions",
          "3": "Estimated useful life extension of 8-10 years"
        }
      },
      "p2": {
        "titulo": "Emergency - Post-Hurricane Restoration",
        "cliente": "EDENORTE",
        "ubicacion": "Santiago, Dominican Republic",
        "tipoServicio": "Emergencies",
        "tipoProducto": "Pole Type Transformers",
        "descripcion": "Restoration of electrical service after a hurricane, including assessment, repair, and installation of transformers.",
        "detalles": "After the hurricane, an emergency team of 25 technicians was mobilized within the first 6 hours. 120 affected transformers were assessed, 85 were repaired on site, and 35 units were replaced with temporary rental equipment. Electrical service was restored to 95% within the first 72 hours.",
        "resultados": {
          "0": "95% of service restored in 72 hours",
          "1": "120 transformers assessed",
          "2": "85 units repaired in the field",
          "3": "35 rental units installed"
        }
      },
      "p3": {
        "titulo": "Engineering - Shopping Mall Substation",
        "cliente": "Agora Mall",
        "ubicacion": "Santo Domingo, DN",
        "tipoServicio": "Engineering and Project Management",
        "tipoProducto": "Substation Transformers",
        "descripcion": "Design, installation, and commissioning of a complete electrical substation for a premium shopping mall.",
        "detalles": "Turnkey project that included substation design, equipment selection, permit management, installation of 3 x 2,500 kVA transformers, medium voltage distribution system, Schneider Electric switchgear, and remote monitoring system. The project was completed 2 weeks ahead of schedule.",
        "resultados": {
          "0": "Delivered 2 weeks ahead of schedule",
          "1": "7,500 kVA installed capacity",
          "2": "24/7 remote monitoring system",
          "3": "Zero safety incidents"
        }
      },
      "p4": {
        "titulo": "Comprehensive Maintenance - Cement Plant",
        "cliente": "Cementos Santo Domingo",
        "ubicacion": "San Cristobal, Dominican Republic",
        "tipoServicio": "Comprehensive Maintenance",
        "tipoProducto": "Power Transformers",
        "descripcion": "Comprehensive maintenance of 8 power transformers at a cement production plant.",
        "detalles": "Comprehensive maintenance was performed on 8 power transformers (2,000-10,000 kVA) during the plant's scheduled shutdown. The scope included tank and radiator cleaning, dielectric oil change, gasket and seal replacement, complete electrical testing, and exterior anticorrosive coating.",
        "resultados": {
          "0": "8 transformers successfully serviced",
          "1": "Compliance with shutdown schedule",
          "2": "15% improvement in operational efficiency",
          "3": "Reduction in operating temperature"
        }
      },
      "p5": {
        "titulo": "Laboratory Testing - Distribution Network",
        "cliente": "EDESUR",
        "ubicacion": "Southern Region, Dominican Republic",
        "tipoServicio": "Laboratory Testing",
        "tipoProducto": "Distribution Transformers",
        "descripcion": "Sampling and dielectric oil analysis campaign for 200 transformers in the distribution network.",
        "detalles": "In partnership with SD Myers, a diagnostic campaign was executed that included oil sampling from 200 transformers, dissolved gas analysis (DGA), dielectric strength, moisture content, acidity, and furan analysis. The results allowed prioritizing 35 units for immediate intervention and planning maintenance for the remaining units.",
        "resultados": {
          "0": "200 samples analyzed",
          "1": "35 units prioritized for intervention",
          "2": "Condition database updated",
          "3": "3-year maintenance plan developed"
        }
      },
      "p6": {
        "titulo": "Temporary Rental - Tourism Project",
        "cliente": "Hard Rock Hotel & Casino",
        "ubicacion": "Punta Cana, Dominican Republic",
        "tipoServicio": "Equipment Rental",
        "tipoProducto": "Pad Mounted Transformers",
        "descripcion": "Temporary power supply during the expansion of the hotel complex.",
        "detalles": "6 Pad Mounted transformers were provided on rental (225-1,000 kVA) for 8 months to cover temporary power needs during the construction phase of the new hotel wing. Transport, installation, commissioning, monthly maintenance, and deinstallation upon project completion were included.",
        "resultados": {
          "0": "8 months of uninterrupted service",
          "1": "Zero power interruptions",
          "2": "Monthly maintenance included",
          "3": "Clean deinstallation upon completion"
        }
      }
    },
    "testimoniales": {
      "t1": {
        "cargo": "Maintenance Manager",
        "testimonio": "Since we implemented the preventive maintenance program with EMINSA, our unplanned failures were reduced by 85%. Their technical team is highly professional and always meets established timelines."
      },
      "t2": {
        "cargo": "Director of Operations",
        "testimonio": "EMINSA's response during the post-hurricane emergency was exceptional. In less than 6 hours they already had a team in the field, and within 72 hours we had restored 95% of service. They are true strategic allies."
      },
      "t3": {
        "cargo": "Director of Projects",
        "testimonio": "The substation project was executed flawlessly. EMINSA not only met all technical specifications but delivered 2 weeks ahead of schedule. The quality of their engineering is first-rate."
      },
      "t4": {
        "cargo": "Plant Manager",
        "testimonio": "The comprehensive maintenance during our scheduled shutdown was executed with military precision. All 8 transformers were left in optimal condition and the plant started up without any setbacks. Excellent service."
      },
      "t5": {
        "cargo": "Distribution Supervisor",
        "testimonio": "EMINSA's laboratory analyses, in partnership with SD Myers, allowed us to identify 35 transformers that required urgent intervention. Thanks to that, we avoided failures that would have cost us millions."
      },
      "t6": {
        "cargo": "Project Manager",
        "testimonio": "The transformer rental service was key to our expansion project. EMINSA provided us with reliable equipment, professional installation, and impeccable maintenance throughout the 8-month contract."
      }
    },
    "clientes": {
      "c1": {
        "sector": "Energy and Distribution",
        "serviciosContratados": {
          "0": "Emergencies",
          "1": "Preventive Maintenance",
          "2": "Rental"
        }
      },
      "c2": {
        "sector": "Energy and Distribution",
        "serviciosContratados": {
          "0": "Laboratory Testing",
          "1": "Preventive Maintenance"
        }
      },
      "c3": {
        "sector": "Energy and Distribution",
        "serviciosContratados": {
          "0": "Comprehensive Maintenance",
          "1": "Emergencies"
        }
      },
      "c4": {
        "sector": "Industrial",
        "serviciosContratados": {
          "0": "Preventive Maintenance",
          "1": "Field Corrective"
        }
      },
      "c5": {
        "sector": "Commercial",
        "serviciosContratados": {
          "0": "Engineering & Projects",
          "1": "Comprehensive Maintenance"
        }
      },
      "c6": {
        "sector": "Industrial",
        "serviciosContratados": {
          "0": "Comprehensive Maintenance",
          "1": "Laboratory Testing"
        }
      },
      "c7": {
        "sector": "Hospitality and Tourism",
        "serviciosContratados": {
          "0": "Equipment Rental",
          "1": "Engineering & Projects"
        }
      },
      "c8": {
        "sector": "Energy and Distribution",
        "serviciosContratados": {
          "0": "Corrective Maintenance",
          "1": "Emergencies"
        }
      },
      "c9": {
        "sector": "Industrial",
        "serviciosContratados": {
          "0": "Preventive Maintenance",
          "1": "Laboratory Testing"
        }
      },
      "c10": {
        "sector": "Commercial",
        "serviciosContratados": {
          "0": "Comprehensive Maintenance",
          "1": "Technical Advisory"
        }
      },
      "c11": {
        "sector": "Healthcare",
        "serviciosContratados": {
          "0": "Preventive Maintenance",
          "1": "Emergencies"
        }
      },
      "c12": {
        "sector": "Commercial",
        "serviciosContratados": {
          "0": "Comprehensive Maintenance",
          "1": "Equipment Rental"
        }
      }
    },
    "recursos": {
      "r1": {
        "nombre": "Order Service",
        "descripcion": "Request a maintenance, repair, or inspection service for your transformers."
      },
      "r2": {
        "nombre": "KVA Calculator",
        "descripcion": "Tool to calculate the required transformer capacity based on your load."
      }
    }
  },
  "eminsa": {
    "info": {
      "fullName": "Grupo Empresarial EMINSA",
      "tagline": "More Than 50 Years of Excellence in the Electrical Sector",
      "slogan": "Comprehensive Solutions in Transformers and Electrical Equipment",
      "description": "GRUPO EMINSA is a leader in the Dominican Republic and the Caribbean in the manufacturing, repair, and commercialization of electrical distribution transformers and related equipment. With more than 50 years of experience, we offer comprehensive solutions backed by the highest international quality standards.",
      "headquarters": "Santo Domingo, Dominican Republic"
    },
    "stats": {
      "0": { "label": "Years of Experience" },
      "1": { "label": "Transformers Installed" },
      "2": { "label": "Satisfied Clients" },
      "3": { "label": "Technical Support" }
    },
    "advantages": {
      "0": {
        "title": "Proven Experience",
        "description": "More than 50 years specializing in electrical distribution transformers in the Caribbean."
      },
      "1": {
        "title": "Certified Quality",
        "description": "ISO 9001:2015 certification and compliance with ANSI, IEEE, and DOE standards."
      },
      "2": {
        "title": "Comprehensive Solutions",
        "description": "From manufacturing to maintenance, repair, and commercialization services."
      },
      "3": {
        "title": "Regional Reach",
        "description": "Consolidated presence in the Dominican Republic and the Caribbean."
      }
    },
    "about": {
      "title": "Grupo EMINSA",
      "description": "GRUPO EMINSA is a leading business organization in the Dominican Republic and the Caribbean, with more than 50 years of experience in the electrical distribution transformer sector and related equipment. We specialize in offering comprehensive solutions that include manufacturing, repair, remanufacturing, commercialization, and specialized technical services.",
      "mission": "To provide reliable, innovative, and quality solutions in transformers and electrical equipment, acting with transparency, integrity, and dedication in every project. Our commitment is to exceed our clients' expectations, guaranteeing exceptional technical service backed by decades of experience.",
      "vision": "To be the leading reference in the Caribbean for the manufacturing, repair, and commercialization of electrical transformers, recognized for our technical excellence, constant innovation, and commitment to the sustainable development of the energy sector.",
      "values": {
        "0": {
          "title": "Excellence",
          "description": "We strive to exceed expectations in every project, ensuring the highest quality in our products and services."
        },
        "1": {
          "title": "Integrity",
          "description": "We act with honesty, transparency, and ethics in all our business relationships and operations."
        },
        "2": {
          "title": "Commitment",
          "description": "We fulfill our promises and take full responsibility for our products, services, and the impact we generate."
        },
        "3": {
          "title": "Innovation",
          "description": "We constantly seek better ways to serve our clients, adopting new technologies and improving our processes."
        }
      },
      "team": "We have a team of highly trained multidisciplinary professionals, engineers, technicians, and specialists committed to providing the best possible solutions. Our staff receives ongoing training to stay up to date with the latest technologies and industry standards.",
      "position": "In the Dominican Republic and the Caribbean, GRUPO EMINSA has established itself as the reference specialist in electrical transformers. Our trajectory of more than five decades, combined with our technical capacity and commitment to quality, has allowed us to earn the trust of hundreds of clients across various industrial, commercial, and residential sectors."
    },
    "divisions": {
      "mtn": {
        "fullName": "New Transformer Manufacturing",
        "description": "Manufacturing of distribution transformers with the highest international quality standards."
      },
      "rst": {
        "fullName": "Transformer Repair and Service",
        "description": "Specialists in the repair and remanufacturing of distribution and industrial transformers."
      },
      "eic": {
        "fullName": "Eminsa International Corporation",
        "description": "Exclusive representatives of the best international brands in electrical equipment."
      },
      "servicios": {
        "fullName": "Specialized Technical Services",
        "description": "Maintenance, repair, and technical support of electrical transformers in the field."
      }
    },
    "milestones": {
      "0": {
        "year": "September 14, 1973",
        "event": "Founding of EMINSA",
        "description": "First company in the Dominican Republic for the manufacturing and repair of electrical distribution transformers.",
        "details": {
          "0": "On September 14, 1973, the Empresa de Ingenieria Electrica SAS (EMINSA) was incorporated, as a result of the merger of Dominican capital with the Chilean multinational company Hernan Briones y Compania.",
          "1": "It is the first company established in the Dominican Republic for the manufacturing and repair of electrical distribution transformers.",
          "2": "In 1979, the company acquired the machinery and equipment from Canadian General Electric, advised by the Canadian firm Ferranti Packard Transformers.",
          "3": "The Pad Mounted transformer was introduced to the market, once again pioneering in this range."
        },
        "achievements": {
          "0": "First transformer factory in the Dominican Republic",
          "1": "Pioneering Dominican-Chilean merger in the sector",
          "2": "Introduction of the Pad Mounted transformer to the market"
        }
      },
      "1": {
        "year": "Late 1980s - 1996",
        "event": "First Exports and International Alliances",
        "description": "Exports to Haiti and Turks & Caicos, and agreement with Energy International Corporation USA.",
        "details": {
          "0": "In the late 1980s, EMINSA made its first exports to the Republic of Haiti, as well as to the Turks & Caicos Islands through an electrical contractor.",
          "1": "In 1996, a technical assistance and raw material supply agreement was signed with the international division of Energy International Corporation in the United States, a firm with more than 100 years of experience.",
          "2": "The agreement covered especially the area of electrical substations and power generation projects."
        },
        "achievements": {
          "0": "First exports to the Caribbean and Haiti",
          "1": "Alliance with Energy International Corporation USA",
          "2": "Presence in multiple Caribbean markets"
        }
      },
      "2": {
        "year": "2002 - 2006",
        "event": "A New Millennium: Diversification and Growth",
        "description": "Distribution of Medium Voltage Switchgear, Dutch PUM advisory, and official ABB distribution.",
        "details": {
          "0": "In 2002, driven by a spirit of constant innovation and customer needs, EMINSA began the distribution of Medium Voltage Switchgear and Transformation Centers.",
          "1": "In 2003, EMINSA received advisory from PUM (Netherlands Senior Experts Program), who redesigned business operations, focusing them on the commercialization of services based on the flexibility and innovation of experienced subcontractors.",
          "2": "In 2006, EMINSA undertook the distribution of ABB, Inc. transformers and equipment, maintaining a stock of transformers available for its clients.",
          "3": "EMINSA was designated as an authorized company for evaluation, diagnostics, and repair services for equipment manufactured by General Electric, CO. in the Dominican Republic."
        },
        "achievements": {
          "0": "Distribution of Medium Voltage Switchgear",
          "1": "Operational redesign with Dutch PUM advisory",
          "2": "Official ABB Inc. distribution",
          "3": "Authorized General Electric service in the Dominican Republic"
        }
      },
      "3": {
        "year": "2018 - 2019",
        "event": "New International Representations",
        "description": "Agreements with an Ecuadorian manufacturer, Schneider Electric USA, and ELPROM TRAFO Bulgaria.",
        "details": {
          "0": "In 2018, a representation agreement was signed with an Ecuadorian Transformer manufacturer, with its own cutting-edge technology and highly qualified professionals, technicians, and operators.",
          "1": "In 2019, EMINSA signed a distribution contract with Schneider Electric USA, a global specialist in energy management and automation with operations in more than 100 countries.",
          "2": "That same year, a representation and distribution contract was signed with the Bulgarian company ELPROM TRAFO, which holds the IEC (International Electrotechnical Commission) standard."
        },
        "achievements": {
          "0": "Representation of an Ecuadorian transformer manufacturer",
          "1": "Official Schneider Electric USA distribution",
          "2": "ELPROM TRAFO Bulgaria representation (IEC standard)"
        }
      },
      "4": {
        "year": "2024",
        "event": "Relocation to Duarte Industrial Park",
        "description": "Preparation to open the first 100% new transformer factory in the Caribbean.",
        "details": {
          "0": "EMINSA relocated its operations to Duarte Industrial Park.",
          "1": "Preparation began to open the first 100% new transformer factory in the Caribbean."
        },
        "achievements": {
          "0": "New facilities at Duarte Industrial Park",
          "1": "Preparation of the first MTN factory in the Caribbean"
        }
      },
      "5": {
        "year": "2025",
        "event": "First MTN Prototypes, ISO 9001, and CEPM Certification",
        "description": "Release of the first new EMINSA transformers manufactured under ANSI / DOE 2016 standards.",
        "details": {
          "0": "The first prototypes of the new EMINSA transformer line were released, manufactured under ANSI standards and with DOE 2016 efficiency.",
          "1": "EMINSA obtained ISO 9001 certification.",
          "2": "CEPM received one of the prototypes of the new EMINSA transformers for technical evaluation.",
          "3": "After completing the testing and validation process, CEPM certified the transformers manufactured by EMINSA for use in their distribution networks."
        },
        "achievements": {
          "0": "First MTN prototypes under ANSI / DOE 2016 standards",
          "1": "ISO 9001 certification obtained",
          "2": "CEPM certification for distribution networks"
        }
      }
    }
  }
}
